azure/__init__.py
azure/mgmt/__init__.py
azure/mgmt/documentdb/__init__.py
azure/mgmt/documentdb/document_db.py
azure/mgmt/documentdb/version.py
azure/mgmt/documentdb/models/__init__.py
azure/mgmt/documentdb/models/consistency_policy.py
azure/mgmt/documentdb/models/database_account.py
azure/mgmt/documentdb/models/database_account_connection_string.py
azure/mgmt/documentdb/models/database_account_create_update_parameters.py
azure/mgmt/documentdb/models/database_account_list_connection_strings_result.py
azure/mgmt/documentdb/models/database_account_list_keys_result.py
azure/mgmt/documentdb/models/database_account_list_read_only_keys_result.py
azure/mgmt/documentdb/models/database_account_paged.py
azure/mgmt/documentdb/models/database_account_patch_parameters.py
azure/mgmt/documentdb/models/database_account_regenerate_key_parameters.py
azure/mgmt/documentdb/models/document_db_enums.py
azure/mgmt/documentdb/models/failover_policies.py
azure/mgmt/documentdb/models/failover_policy.py
azure/mgmt/documentdb/models/location.py
azure/mgmt/documentdb/models/resource.py
azure/mgmt/documentdb/operations/__init__.py
azure/mgmt/documentdb/operations/database_accounts_operations.py
azure_mgmt_documentdb-0.1.4.dist-info/LICENSE
azure_mgmt_documentdb-0.1.4.dist-info/METADATA
azure_mgmt_documentdb-0.1.4.dist-info/WHEEL
azure_mgmt_documentdb-0.1.4.dist-info/top_level.txt
azure_mgmt_documentdb-0.1.4.dist-info/RECORD
