Metadata-Version: 2.1
Name: azure-mgmt-documentdb
Version: 0.1.4
Summary: Microsoft Azure DocumentDB Management Client Library for Python
Home-page: https://github.com/Azure/azure-sdk-for-python
Author: Microsoft Corporation
Author-email: ptvshelp@microsoft.com
License: MIT License
Keywords: azure,azure sdk
Classifier: Development Status :: 7 - Inactive
Classifier: Programming Language :: Python
Classifier: Programming Language :: Python :: 3 :: Only
Classifier: Programming Language :: Python :: 3
Classifier: Programming Language :: Python :: 3.3
Classifier: Programming Language :: Python :: 3.4
Classifier: Programming Language :: Python :: 3.5
Classifier: License :: OSI Approved :: MIT License
License-File: LICENSE
Requires-Dist: msrestazure ~=0.4.7
Requires-Dist: azure-common ~=1.1.5
Requires-Dist: None >=2.0.0
